regener/classes/pdf.py
regener/regener.py
regener-22.7.18.dist-info/entry_points.txt
regener-22.7.18.dist-info/WHEEL
regener-22.7.18.dist-info/METADATA
regener-22.7.18.dist-info/RECORD
