Metadata-Version: 2.1
Name: regener
Version: 22.7.18
Summary: Regener - Resume Generator
Home-page: http://github.com/8tm/regener
Author: Tadeusz Miszczyk
Author-email: 42252259+8tm@users.noreply.github.com
Requires-Python: >=3.7.0,<4.0.0
Classifier: Environment :: Console
Classifier: Intended Audience :: Developers
Classifier: Operating System :: Unix
Classifier: Programming Language :: Python :: 3
Classifier: Programming Language :: Python :: 3 :: Only
Classifier: Programming Language :: Python :: 3.10
Classifier: Programming Language :: Python :: 3.7
Classifier: Programming Language :: Python :: 3.8
Classifier: Programming Language :: Python :: 3.9
Requires-Dist: fpdf2 (>=2.5.0,<3.0.0)
Project-URL: Documentation, https://test.pypi.org/project/regener
Project-URL: Repository, http://github.com/8tm/regener
